zoo_cmd/__init__.py
zoo_cmd/cmd_register.py
zoo_cmd/main.py
zoo_cmd/cmds/__init__.py
zoo_cmd/cmds/cmd_addauth.py
zoo_cmd/cmds/cmd_cat.py
zoo_cmd/cmds/cmd_cd.py
zoo_cmd/cmds/cmd_cdcd.py
zoo_cmd/cmds/cmd_ls.py
zoo_cmd/cmds/cmd_pwd.py
zoo_cmd/cmds/cmd_rm.py
zoo_cmd/cmds/cmd_set.py
zoo_cmd/cmds/cmd_touch.py
zoo_cmd/cmds/cmd_vi.py
zoo_cmd/cmds/cmd_wc.py
zoo_cmd/zk/__init__.py
zoo_cmd/zk/zk_opers.py
zoo_cmd-1.1.0.dist-info/METADATA
zoo_cmd-1.1.0.dist-info/WHEEL
zoo_cmd-1.1.0.dist-info/entry_points.txt
zoo_cmd-1.1.0.dist-info/top_level.txt
zoo_cmd-1.1.0.dist-info/RECORD
