Metadata-Version: 2.1
Name: zoo-cmd
Version: 1.1.0
Summary: zookeeper cli client
Home-page: https://github.com/liujinliu/zoo_cmd
Author: liujinliu
Author-email: UNKNOWN
License: Apache
Platform: UNKNOWN
Classifier: Environment :: Console
Requires-Dist: kazoo
